package/__init__.py
package/subha.py
package/subha1.py
Subha_Myproject-100.1.dist-info/LICENSE
Subha_Myproject-100.1.dist-info/METADATA
Subha_Myproject-100.1.dist-info/WHEEL
Subha_Myproject-100.1.dist-info/top_level.txt
Subha_Myproject-100.1.dist-info/RECORD
